rsyncsqlite/__init__.py
rsyncsqlite/context.py
rsyncsqlite-0.1.0.dist-info/WHEEL
rsyncsqlite-0.1.0.dist-info/entry_points.txt
rsyncsqlite-0.1.0.dist-info/METADATA
rsyncsqlite-0.1.0.dist-info/RECORD
