Metadata-Version: 2.3
Name: rsyncsqlite
Version: 0.1.0
Summary: A python wrapper around sqlite3_rsync for easy access to remote databases
Author: Jan Neuendorf
Requires-Python: >=3.12
